pysignalclirestapi/__init__.py
pysignalclirestapi/api.py
pysignalclirestapi/helpers.py
pysignalclirestapi-0.3.24.dist-info/LICENSE.txt
pysignalclirestapi-0.3.24.dist-info/METADATA
pysignalclirestapi-0.3.24.dist-info/WHEEL
pysignalclirestapi-0.3.24.dist-info/top_level.txt
pysignalclirestapi-0.3.24.dist-info/RECORD
