Metadata-Version: 2.1
Name: pysignalclirestapi
Version: 0.3.24
Summary: Small python library for the Signal Cli REST API
Home-page: https://github.com/bbernhard/pysignalclirestapi
Author: Bernhard B.
Author-email: bernhard@liftingcoder.com
License: UNKNOWN
Platform: UNKNOWN
Classifier: Programming Language :: Python :: 3
Classifier: License :: OSI Approved :: MIT License
Classifier: Operating System :: OS Independent
Requires-Python: >=2.7
License-File: LICENSE.txt
Requires-Dist: requests
Requires-Dist: six
